{
  "slug": "202-hometown-tacos",
  "handle": "202_hometown_tacos_",
  "followers": 6168,
  "follows": 6914,
  "posts_total": 560,
  "posts_30d": 9,
  "reels_30d": 1,
  "avg_engagement_rate": 0.00786,
  "verified": false,
  "private": false,
  "is_business_account": false,
  "biography": "Restaurant\nTaco Bar w/ outdoor Patio\n15 mins from the city\n407 Lincoln Avenue, Bellevue, Pennsylvania",
  "full_name": "",
  "last_post_at": "2026-05-13T16:43:18.000Z",
  "scraped_at": "2026-05-13T19:26:11.214Z",
  "growth": null
}
