{
  "slug": "chikn",
  "handle": "hotchikn",
  "followers": 6769,
  "follows": 478,
  "posts_total": 811,
  "posts_30d": 7,
  "reels_30d": 3,
  "avg_engagement_rate": 0.00322,
  "verified": false,
  "private": false,
  "is_business_account": true,
  "biography": "LOCATIONS\n📍3712 Forbes Avenue \n📍 20018 Rt 19 \n📍1740 Settlers Ridge Center Dr \n📸share your pics with us#hotchikn",
  "full_name": "CHiKN",
  "last_post_at": "2026-05-12T15:49:11.000Z",
  "scraped_at": "2026-05-13T19:26:11.214Z",
  "growth": null
}
