{
  "slug": "esspa-kozmetika-organic-day-spa-and-skincare-salon",
  "handle": "esspa_organic",
  "followers": 6898,
  "follows": 1032,
  "posts_total": 1047,
  "posts_30d": 11,
  "reels_30d": 8,
  "avg_engagement_rate": 0.00858,
  "verified": true,
  "private": false,
  "is_business_account": true,
  "biography": "ESSpa | Pittsburgh  \nHungarian Organic Wellness 🌿  \nWe don’t chase trends — we build skin longevity  \nFace • Body • Hair • Nails • Massage  \n⬇️ Book",
  "full_name": "ESSpa Skincare & Beauty | Pittsburgh",
  "last_post_at": "2026-05-13T01:04:00.000Z",
  "scraped_at": "2026-05-13T19:26:11.214Z",
  "growth": null
}
