{
  "slug": "evolve-massage-and-wellness-center",
  "handle": "evolvespa_scotttwp",
  "followers": 415,
  "follows": 73,
  "posts_total": 119,
  "posts_30d": 0,
  "reels_30d": 0,
  "avg_engagement_rate": 0.01229,
  "verified": true,
  "private": false,
  "is_business_account": true,
  "biography": "Evolve Massage & Wellness Center is a locally-owned and operated health spa. We offer customized treatments to improve your overall health!",
  "full_name": "Evolve Massage & Wellness",
  "last_post_at": "2025-05-22T16:12:29.000Z",
  "scraped_at": "2026-05-13T19:26:11.214Z",
  "growth": null
}
