{
  "slug": "fresh-from-the-farm-juices",
  "handle": "freshfromthefarmjuices",
  "followers": 2573,
  "follows": 1695,
  "posts_total": 680,
  "posts_30d": 1,
  "reels_30d": 1,
  "avg_engagement_rate": 0.00373,
  "verified": false,
  "private": false,
  "is_business_account": true,
  "biography": "Raw and Organic Salads, Wraps, and Cold-Pressed Juices",
  "full_name": "Fresh From The Farm Juices",
  "last_post_at": "2026-05-12T16:21:18.000Z",
  "scraped_at": "2026-05-13T19:26:11.214Z",
  "growth": null
}
