{
  "slug": "harper-and-pennys",
  "handle": "harperpennys",
  "followers": 3427,
  "follows": 313,
  "posts_total": 302,
  "posts_30d": 0,
  "reels_30d": 0,
  "avg_engagement_rate": 0.00496,
  "verified": false,
  "private": false,
  "is_business_account": true,
  "biography": "Elevated American fare in Lansdale, paired with craft brews from Round Guys. 🍔🍺🤘\nTues - Fri: 4pm - 10pm\nSat: 12pm-11pm\nSun: 12pm-8:30pm\nMon: Closed",
  "full_name": "Harper&Pennys",
  "last_post_at": "2026-01-23T05:27:24.000Z",
  "scraped_at": "2026-05-13T19:26:11.214Z",
  "growth": null
}
