{
  "slug": "ka-fair-coffee-and-cakery",
  "handle": "kafair_cafe",
  "followers": 2594,
  "follows": 617,
  "posts_total": 417,
  "posts_30d": 3,
  "reels_30d": 0,
  "avg_engagement_rate": 0.01739,
  "verified": false,
  "private": false,
  "is_business_account": true,
  "biography": "1806 chislett \nmorningside of pittsburgh pennsylvania\nOpen Monday-Friday 7:00am - 3:00pm\n           Sat-Sunday.      8:00am- 3:00pm",
  "full_name": "Ka-Fair",
  "last_post_at": "2026-04-21T18:23:56.000Z",
  "scraped_at": "2026-04-22T15:26:15.591Z",
  "growth": null,
  "tiktok_mentions": {
    "query": "ka-fair coffee and cakery pittsburgh",
    "video_count": 0,
    "total_plays": 0,
    "total_likes": 0,
    "unique_creators": 0,
    "top_creators": [],
    "top_videos": [],
    "most_recent_post_at": null,
    "median_plays": 0,
    "detected_own_handle": null,
    "scraped_at": "2026-04-26T15:59:35.679Z"
  }
}