{
  "slug": "la-famiglia-gourmet-pizza-company",
  "handle": "lafamigliagourmetpizzaco",
  "followers": 403,
  "follows": 281,
  "posts_total": 430,
  "posts_30d": 9,
  "reels_30d": 5,
  "avg_engagement_rate": 0.02134,
  "verified": false,
  "private": false,
  "is_business_account": true,
  "biography": "Offering the finest in gourmet pizzas, hoagies, wings and more 🍕\n⏰Sun-Thur: 11am-8pm\n⏰Fri-Sat: 11am-9pm\nOrder online for carryout and delivery",
  "full_name": "La Famiglia Gourmet Pizza Company",
  "last_post_at": "2026-05-11T12:06:42.000Z",
  "scraped_at": "2026-05-13T19:26:11.214Z",
  "growth": null,
  "tiktok_mentions": {
    "query": "la famiglia gourmet pizza pittsburgh",
    "video_count": 0,
    "total_plays": 0,
    "total_likes": 0,
    "unique_creators": 0,
    "top_creators": [],
    "top_videos": [],
    "most_recent_post_at": null,
    "median_plays": 0,
    "detected_own_handle": null,
    "scraped_at": "2026-06-10T19:22:49.060Z"
  }
}