{
  "slug": "lincolns-p-g-diner",
  "handle": "lincolnspgdiner",
  "followers": 1026,
  "follows": 104,
  "posts_total": 382,
  "posts_30d": 9,
  "reels_30d": 0,
  "avg_engagement_rate": 0.00828,
  "verified": false,
  "private": false,
  "is_business_account": true,
  "biography": "Home of the Big Lincoln 🍳🥓🥞☕\nProudly serving  #Millvale since 1928\nOpen daily at 8am for dine-in or take-out\nTime to eat 🕗",
  "full_name": "Lincoln's P&G Diner",
  "last_post_at": "2026-05-08T17:35:44.000Z",
  "scraped_at": "2026-05-13T19:26:11.214Z",
  "growth": null
}
