{
  "slug": "market-district-supermarket-rhqzqk",
  "handle": "marketdistrict",
  "followers": 24139,
  "follows": 348,
  "posts_total": 1332,
  "posts_30d": 6,
  "reels_30d": 4,
  "avg_engagement_rate": 0.02653,
  "verified": true,
  "private": false,
  "is_business_account": true,
  "biography": "The official Instagram page of Market District! Tag your pictures #marketdistrict to be featured!",
  "full_name": "Market District",
  "last_post_at": "2026-05-08T17:54:30.000Z",
  "scraped_at": "2026-05-13T19:26:11.214Z",
  "growth": null
}
