{
  "slug": "nicholas-coffee-tea-co",
  "handle": "nicholascoffeepgh",
  "followers": 2589,
  "follows": 531,
  "posts_total": 160,
  "posts_30d": 3,
  "reels_30d": 0,
  "avg_engagement_rate": 0.05052,
  "verified": false,
  "private": false,
  "is_business_account": false,
  "biography": "PGH coffee roaster ☕️\nM-F: 7:00AM-3:30PM\nSat: 8:30-3:30PM\nClosed Sunday \nBuy online ⬇️",
  "full_name": "Nicholas Coffee",
  "last_post_at": "2026-04-24T13:15:22.000Z",
  "scraped_at": "2026-05-13T19:26:11.214Z",
  "growth": null
}
