{
  "slug": "save-a-lot",
  "handle": "savealotfoodstores",
  "followers": 19036,
  "follows": 166,
  "posts_total": 1437,
  "posts_30d": 12,
  "reels_30d": 4,
  "avg_engagement_rate": 0.0006,
  "verified": true,
  "private": false,
  "is_business_account": true,
  "biography": "✨Offering quality without compromise\n🍅Fresh meat, quality produce and all of your grocery needs\n💵100% Money Back Guarantee",
  "full_name": "Save A Lot",
  "last_post_at": "2026-05-11T18:09:12.000Z",
  "scraped_at": "2026-05-13T19:26:11.214Z",
  "growth": null
}
