{
  "slug": "southside-tattoo-body-piercing",
  "handle": "southsidetattoo",
  "followers": 7682,
  "follows": 1155,
  "posts_total": 978,
  "posts_30d": 2,
  "reels_30d": 0,
  "avg_engagement_rate": 0.00353,
  "verified": false,
  "private": false,
  "is_business_account": true,
  "biography": "Artist: Veronica,@brandondauberger ,@mikehluhanart ,@garricksstattoo  Piercers:@jewelshelmich ,@dan_dimond . 23+ years on the Southside of Pittsburgh",
  "full_name": "Southside Tattoo Body Piercing",
  "last_post_at": "2026-04-23T17:54:59.000Z",
  "scraped_at": "2026-05-13T19:26:11.214Z",
  "growth": null
}
