{
  "slug": "truss-brewing-company",
  "handle": "trussbrewingcompany",
  "followers": 2073,
  "follows": 29,
  "posts_total": 637,
  "posts_30d": 12,
  "reels_30d": 0,
  "avg_engagement_rate": 0.00289,
  "verified": false,
  "private": false,
  "is_business_account": true,
  "biography": "A take-out only nano-brewery and wood-fired oven restaurant.     Open Wed - Sat from 11a -10p",
  "full_name": "TRUSS Brewing Company",
  "last_post_at": "2026-05-12T14:06:49.000Z",
  "scraped_at": "2026-05-13T19:26:11.214Z",
  "growth": null
}
